mijnah/__init__.py
mijnah/cart.py
mijnah/product.py
mijnah-1.2.0.data/data/.VERSION
mijnah-1.2.0.data/data/LICENSE
mijnah-1.2.0.data/data/README.md
mijnah-1.2.0.dist-info/LICENSE
mijnah-1.2.0.dist-info/METADATA
mijnah-1.2.0.dist-info/WHEEL
mijnah-1.2.0.dist-info/top_level.txt
mijnah-1.2.0.dist-info/RECORD
