Metadata-Version: 2.1
Name: mijnah
Version: 1.2.0
Summary: mijn albert heijn library
Home-page: https://github.com/frejonb/mijn-albert-heijn
Author: F. G. Rejon Barrera
Author-email: f.g.rejonbarrera@gmail.com
License: UNKNOWN
Keywords: albert heijn
Platform: UNKNOWN
Requires-Dist: requests (==2.22.0)
